LICENSE
README.md
setup.cfg
setup.py
carefree_cli.egg-info/PKG-INFO
carefree_cli.egg-info/SOURCES.txt
carefree_cli.egg-info/dependency_links.txt
carefree_cli.egg-info/entry_points.txt
carefree_cli.egg-info/requires.txt
carefree_cli.egg-info/top_level.txt
cfi/__init__.py
cfi/common.py
cfi/console.py
cfi/constants.py
cfi/schema.py
cfi/utils.py
cfi/crud/__init__.py
cfi/crud/create.py
cfi/crud/delete.py
cfi/crud/read.py
cfi/crud/update.py
cfi/meta/__init__.py
cfi/meta/export_fn.py
cfi/meta/import_fn.py
cfi/meta/init.py
cfi/meta/list.py