Metadata-Version: 2.1
Name: carefree-cli
Version: 0.1.2
Summary: A `cli` that helps you manage your commands
Home-page: https://github.com/carefree0910/carefree-cli
Download-URL: https://github.com/carefree0910/carefree-cli/archive/v0.1.2.tar.gz
Author: carefree0910
Author-email: syameimaru.saki@gmail.com
Keywords: python cli
License-File: LICENSE
Requires-Dist: rich
Requires-Dist: regex
Requires-Dist: typer
Requires-Dist: filelock
Requires-Dist: pydantic
